offish/__init__.py
offish/formatter.py
offish/version.py
offish-0.0.2.dist-info/LICENSE
offish-0.0.2.dist-info/METADATA
offish-0.0.2.dist-info/WHEEL
offish-0.0.2.dist-info/top_level.txt
offish-0.0.2.dist-info/RECORD
