Metadata-Version: 2.1
Name: offish
Version: 0.0.2
Summary: offish
Author-email: offish <overutilization@gmail.com>
Project-URL: Homepage, https://github.com/offish/py-offish
Project-URL: Bug Tracker, https://github.com/offish/py-offish/issues
Keywords: offish
Classifier: Programming Language :: Python :: 3
Classifier: License :: OSI Approved :: MIT License
Classifier: Operating System :: OS Independent
Requires-Python: >=3.10
License-File: LICENSE
Requires-Dist: requests
